{
  "basics": {
    "name": "Maciej Kasprzyk",
    "label": "DevOps & Software Developer",
    "picture": "",
    "email": "mkasprzyk@szy.fr",
    "phone": "+48 534 581 288",
    "website": "integrate.pl",
    "summary": "Experienced DevOps & Software Developer focused on developing services, managing infrastructure as code, cloud computing and deployment processes",
    "location": {
      "address": "Legionów 102D",
      "postalCode": "81-472",
      "city": "Gdynia",
      "countryCode": "",
      "region": ""
    },
    "profiles": [
      {
        "network": "GitHub",
        "username": "mkasprzyk",
        "url": "https://github.com/mkasprzyk/"
      },
      {
        "network": "LinkedIn",
        "username": "mkasprzyk71",
        "url": "https://www.linkedin.com/in/mkasprzyk71/"
      }
    ]
  },
  "work": [
    {
      "company": "Shareablee",
      "position": "DevOps Engineer",
      "website": "https://www.shareablee.com",
      "startDate": "2019-01-03",
      "summary": "Helping data freaks with things beyond DevOps horizon",
       "highlights": [
        "Building and maintaining Apache Druid cluster from scratch",
        "Developing data pipelines with Apache Spark, Kafka, Airflow and many more",
        "Managing multi-cloud infrastructure with AWS and Azure",
        "Developing tools for various purposes like a migration of terabytes of data",
        "Developing CI/CD pipelines",
        "Taking care about code quality with SonarQube",
        "Many, many more"
      ]
    },
    {
      "company": "SoftServe",
      "position": "DevOps Engineer",
      "website": "https://www.softserveinc.com",
      "startDate": "2018-01-02",
      "endDate": "2018-06-30",
      "summary": "DevOpsing for outsouring company",
       "highlights": [
        "Migrating obsolete build system to google GN"
      ]
    },
    {
      "company": "Tetramatic",
      "position": "DevOps & Software Developer",
      "website": "http://tetramatic.com",
      "startDate": "2016-05-01",
      "summary": "Delivering first-class solutions in DevOps & Software Development area",
       "highlights": [
        "Developing IT services for industries",
        "Building and managing infrastructures & platforms",
        "Implementing best practices in IT world",
        "Optimizing business processes"
      ]
    },
    {
      "company": "Credit Agricole (via Core Services)",
      "position": "Software Integration Engineer (SCM)",
      "website": "https://www.credit-agricole.pl",
      "startDate": "2016-11-01",
      "endDate": "2017-12-31",
      "summary": "DevOpsing + R&D in project focused on private and corporate banking",
      "highlights": [
        "Building internal containerization platform based on OpenShift",
        "Developing configuration management database",
        "Automating business processes"
      ]
    },
    {
      "company": "OVH",
      "position": "DevOps",
      "website": "https://www.ovh.com",
      "startDate": "2016-03-01",
      "endDate": "2016-05-30",
      "summary": "DevOpsing & OpenStack development in one of the biggest hosting company in Europe",
      "highlights": [
        "Developing OpenStack core components and extensions",
        "Automation of systems and processes in public cloud area"
      ]
    },
    {
      "company": "Credit Agricole (via IT Kontrakt)",
      "position": "Software Integration Engineer (SCM)",
      "website": "https://www.credit-agricole.pl",
      "startDate": "2015-11-01",
      "endDate": "2016-03-30",
      "summary": "SCM & software development in project focused on private and corporate banking",
      "highlights": [
        "Developing processes and tools for software deliveries from external software development companies",
        "Introducing cutting-edge technologies in infrastructure management area",
        "Planning future of internal enterprise architecture"
      ]
    },
    {
      "company": "Nokia Networks",
      "position": "Software Integration Engineer (SCM)",
      "website": "https://networks.nokia.com",
      "startDate": "2013-02-01",
      "endDate": "2015-10-01",
      "summary": "Software configuration management & software development in project focused on control plane in mobile broadband ",
      "highlights": [
        "Developing and optimizing continuous integration/deployment tools and processes",
        "Migrating software development and testing processes to containerized environments",
        "Administration of Linux systems, including usage of configuration management tools",
        "Software quality assurance analysis",
        "Managing internal cloud infrastructure"
      ]
    }
  ],
  "volunteer": [],
  "education": [
    {
      "institution": "The ICT and Electronic Schools Complex",
      "area": "ICT",
      "studyType": "technical college",
      "startDate": "2007-09-01",
      "endDate": "2011-06-01",
      "gpa": "",
      "courses": []
    }
  ],
  "awards": [],
  "publications": [],
  "skills": [
    {
      "name": "Scripting",
      "level": "",
      "keywords": [
        "python",
        "bash",
        "groovy"
      ]
    },
    {
      "name": "VCS",
      "level": "",
      "keywords": [
        "git",
        "subversion"
      ]
    },
    {
      "name": "Containers",
      "level": "",
      "keywords": [
        "Docker",
        "Kubernetes",
        "OpenShift",
        "Rancher"
      ]
    },
    {
      "name": "AWS",
      "level": "",
      "keywords": [
        "EC2",
        "MSK",
        "EKS",
        "ECS",
        "RDS",
        "S3",
        "Athena",
        "Beanstalk",
        "Lambda",
        "IoT"
      ]
    },
    {
      "name": "CI/CD",
      "level": "",
      "keywords": [
        "Jenkins",
        "Travis CI",
        "Circle CI",
        "Buildbot",
        "Teamcity"
      ]
    },
    {
      "name": "Virtualization",
      "level": "",
      "keywords": [
        "OpenStack",
        "VMWare vSphere",
        "Eucalyptus",
        "KVM"
      ]
    },
    {
      "name": "Infrastructure as Code",
      "level": "",
      "keywords": [
        "Puppet",
        "Ansible",
        "Terraform",
        "CloudFormation"
      ]
    },
    {
      "name": "Analytics and Monitoring",
      "level": "",
      "keywords": [
        "Prometheus",
        "Alertmanager",
        "CloudWatch",
        "Elastic APM",
        "Kibana",
        "Graylog",
        "Superset",
        "Icinga",
        "Grafana",
        "SonarQube"
      ]
    },
    {
      "name": "Programming languages",
      "level": "",
      "keywords": [
        "Python",
        "Java",
        "JavaScript",
        "Rust"
      ]
    },
    {
      "name": "Databases",
      "level": "",
      "keywords": [
        "Apache Druid",
        "Apache Cassandra",
        "Elasticsearch",
        "PostgreSQL"
      ]
    },
    {
      "name": "Big Data",
      "level": "",
      "keywords": [
        "Apache Spark",
        "Apache Airflow",
        "Apache Kafka"
      ]
    },
    {
      "name": "Operating Systems",
      "level": "",
      "keywords": [
        "Linux",
        "macOS",
        "Windows"
      ]
    }
  ],
  "languages": [
    {
      "language": "Polish",
      "fluency": "Native speaker"
    },
    {
      "language": "English",
      "fluency": "Very good command of spoken and written English"
    }
  ],
  "interests": [],
  "references": []
}
